<?xml version="1.0" encoding="utf-8"?>
<Argos version="1.1">
	<list id="homographies">
		<Matrix>
			<matrix id="data" rows="3" cols="3">
0.99999999999999967 6.2602082255241282e-016 -5.7310732498271386e-014 
-6.2602082255241282e-016 0.99999999999999967 7.0287460747497921e-013 
0 0 1 
</matrix>
		</Matrix>
		<Matrix>
			<matrix id="data" rows="3" cols="3">
1.0000759796757244 0.00072469755868614927 -0.94805199472233515 
-0.00072469755868614927 1.0000759796757244 0.36882920774605238 
0 0 1 
</matrix>
		</Matrix>
		<Matrix>
			<matrix id="data" rows="3" cols="3">
0.99987188147062234 0.00024921936046632808 -0.31305451837437626 
-0.00024921936046632808 0.99987188147062234 0.19671021000310537 
0 0 1 
</matrix>
		</Matrix>
		<Matrix>
			<matrix id="data" rows="3" cols="3">
0.9994508697341048 0.00078662190129171893 -0.89642010183738297 
-0.00078662190129171893 0.9994508697341048 0.59951603856754188 
0 0 1 
</matrix>
		</Matrix>
		<Matrix>
			<matrix id="data" rows="3" cols="3">
0.99975242613174109 0.0011145473311587007 -0.74264855549299047 
-0.0011145473311587007 0.99975242613174109 0.87547855423188459 
0 0 1 
</matrix>
		</Matrix>
		<Matrix>
			<matrix id="data" rows="3" cols="3">
0.99943614537373726 0.00038572884273498651 -0.17745816572438777 
-0.00038572884273498651 0.99943614537373726 0.61884684825507397 
0 0 1 
</matrix>
		</Matrix>
		<Matrix>
			<matrix id="data" rows="3" cols="3">
0.99974142612107175 0.0011122218741876034 -1.0096498289380031 
-0.0011122218741876034 0.99974142612107175 0.76085136390168184 
0 0 1 
</matrix>
		</Matrix>
		<Matrix>
			<matrix id="data" rows="3" cols="3">
0.9995628188279263 0.00081227080233278498 -0.7360127854194054 
-0.00081227080233278498 0.9995628188279263 0.68986685378345602 
0 0 1 
</matrix>
		</Matrix>
		<Matrix>
			<matrix id="data" rows="3" cols="3">
0.99975090784411702 0.001298776435938924 -1.3579811158131156 
-0.001298776435938924 0.99975090784411702 0.83848957657231293 
0 0 1 
</matrix>
		</Matrix>
		<Matrix>
			<matrix id="data" rows="3" cols="3">
0.99977062129249428 0.0010496136743899599 -0.89871913486689581 
-0.0010496136743899599 0.99977062129249428 0.73763302370554196 
0 0 1 
</matrix>
		</Matrix>
		<Matrix>
			<matrix id="data" rows="3" cols="3">
0.99968210871099961 0.00099522389419112798 -1.0660958197512789 
-0.00099522389419112798 0.99968210871099961 0.75668787237248736 
0 0 1 
</matrix>
		</Matrix>
		<Matrix>
			<matrix id="data" rows="3" cols="3">
0.9997416725865409 0.0010265781647645364 -0.95758447123628132 
-0.0010265781647645364 0.9997416725865409 0.75675427943339424 
0 0 1 
</matrix>
		</Matrix>
		<Matrix>
			<matrix id="data" rows="3" cols="3">
0.99966841750843616 0.001217340463613133 -1.0515167316562131 
-0.001217340463613133 0.99966841750843616 1.0177665458430831 
0 0 1 
</matrix>
		</Matrix>
		<Matrix>
			<matrix id="data" rows="3" cols="3">
0.99989636723244302 0.0013643344441688517 -1.2013574129319935 
-0.0013643344441688517 0.99989636723244302 1.0022106672311215 
0 0 1 
</matrix>
		</Matrix>
		<Matrix>
			<matrix id="data" rows="3" cols="3">
0.99943963352733767 0.0010543216314161182 -0.68385269577871943 
-0.0010543216314161182 0.99943963352733767 0.97728416349296066 
0 0 1 
</matrix>
		</Matrix>
		<Matrix>
			<matrix id="data" rows="3" cols="3">
0.99935916299771266 0.0011427110104959839 -0.88147589301417217 
-0.0011427110104959839 0.99935916299771266 1.0045443931179687 
0 0 1 
</matrix>
		</Matrix>
		<Matrix>
			<matrix id="data" rows="3" cols="3">
0.99938600016557699 0.00078734987334683063 -0.4372710223873062 
-0.00078734987334683063 0.99938600016557699 0.993707432280588 
0 0 1 
</matrix>
		</Matrix>
		<Matrix>
			<matrix id="data" rows="3" cols="3">
0.9991290506474616 0.0007285899058501015 -0.33776405850812657 
-0.0007285899058501015 0.9991290506474616 0.98050322255528344 
0 0 1 
</matrix>
		</Matrix>
		<Matrix>
			<matrix id="data" rows="3" cols="3">
0.99912963921553433 0.00066622232285841866 -0.28270929909952597 
-0.00066622232285841866 0.99912963921553433 0.9107717769425373 
0 0 1 
</matrix>
		</Matrix>
		<Matrix>
			<matrix id="data" rows="3" cols="3">
0.99917621418456892 0.00033188486311866775 0.22438489508436599 
-0.00033188486311866775 0.99917621418456892 0.83154787238677685 
0 0 1 
</matrix>
		</Matrix>
		<Matrix>
			<matrix id="data" rows="3" cols="3">
0.99885719661290273 0.00013147329774704347 0.46196072754306761 
-0.00013147329774704347 0.99885719661290273 0.82479322138402766 
0 0 1 
</matrix>
		</Matrix>
		<Matrix>
			<matrix id="data" rows="3" cols="3">
0.99888186510799626 0.00027702889614833996 0.19127450533724671 
-0.00027702889614833996 0.99888186510799626 0.7043367700359785 
0 0 1 
</matrix>
		</Matrix>
		<Matrix>
			<matrix id="data" rows="3" cols="3">
0.99880021342440273 -7.6709585829799764e-005 0.70749895608396862 
7.6709585829799764e-005 0.99880021342440273 0.72785812180357312 
0 0 1 
</matrix>
		</Matrix>
		<Matrix>
			<matrix id="data" rows="3" cols="3">
0.99888436081160847 -0.0001053030126717858 0.58623166907746327 
0.0001053030126717858 0.99888436081160847 0.4803978736783252 
0 0 1 
</matrix>
		</Matrix>
		<Matrix>
			<matrix id="data" rows="3" cols="3">
0.99924325238583644 -0.00019505305273424578 0.085766475931859709 
0.00019505305273424578 0.99924325238583644 -0.033258736953265811 
0 0 1 
</matrix>
		</Matrix>
		<Matrix>
			<matrix id="data" rows="3" cols="3">
1.0000874583090287 -0.00092276381888538078 -0.31336810562720058 
0.00092276381888538078 1.0000874583090287 -1.4496832237186961 
0 0 1 
</matrix>
		</Matrix>
		<Matrix>
			<matrix id="data" rows="3" cols="3">
1.006500665202688 -0.0069361424672824065 -3.3012686749316673 
0.0069361424672824065 1.006500665202688 -13.720210308180507 
0 0 1 
</matrix>
		</Matrix>
		<Matrix>
			<matrix id="data" rows="3" cols="3">
1.012943282970193 -0.011743036738097491 -3.8755865513261392 
0.011743036738097491 1.012943282970193 -27.339521047548157 
0 0 1 
</matrix>
		</Matrix>
		<Matrix>
			<matrix id="data" rows="3" cols="3">
1.0156898676707347 -0.016414484593830582 -3.170474582884292 
0.016414484593830582 1.0156898676707347 -34.220813622723462 
0 0 1 
</matrix>
		</Matrix>
		<Matrix>
			<matrix id="data" rows="3" cols="3">
1.0197975802319834 -0.021203084526087372 -2.4374802572522656 
0.021203084526087372 1.0197975802319834 -45.549044950586278 
0 0 1 
</matrix>
		</Matrix>
		<Matrix>
			<matrix id="data" rows="3" cols="3">
1.0191934266105098 -0.035161710550834585 8.447237946739552 
0.035161710550834585 1.0191934266105098 -60.400188671974547 
0 0 1 
</matrix>
		</Matrix>
		<Matrix>
			<matrix id="data" rows="3" cols="3">
1.0199605900500957 -0.032767672930468943 4.4986986736215799 
0.032767672930468943 1.0199605900500957 -59.208162560806315 
0 0 1 
</matrix>
		</Matrix>
		<Matrix>
			<matrix id="data" rows="3" cols="3">
1.0313339797060677 -0.039347490892216369 0.31570831986394943 
0.039347490892216369 1.0313339797060677 -76.865888555846396 
0 0 1 
</matrix>
		</Matrix>
		<Matrix>
			<matrix id="data" rows="3" cols="3">
1.0417909104199541 -0.049348501298735671 -2.3615455445435591 
0.049348501298735671 1.0417909104199541 -96.355928191057245 
0 0 1 
</matrix>
		</Matrix>
		<Matrix>
			<matrix id="data" rows="3" cols="3">
1.0510766067012185 -0.050123319994535426 -11.313134624748336 
0.050123319994535426 1.0510766067012185 -106.60295160981492 
0 0 1 
</matrix>
		</Matrix>
		<Matrix>
			<matrix id="data" rows="3" cols="3">
1.0621809767631549 -0.053451528873082632 -17.725951290802065 
0.053451528873082632 1.0621809767631549 -118.60868658553112 
0 0 1 
</matrix>
		</Matrix>
		<Matrix>
			<matrix id="data" rows="3" cols="3">
1.0644066196793853 -0.053884927762000608 -18.963914493123326 
0.053884927762000608 1.0644066196793853 -120.43980307025785 
0 0 1 
</matrix>
		</Matrix>
		<Matrix>
			<matrix id="data" rows="3" cols="3">
1.0641221537972221 -0.053661420258170708 -19.730369412948434 
0.053661420258170708 1.0641221537972221 -120.36382784611232 
0 0 1 
</matrix>
		</Matrix>
		<Matrix>
			<matrix id="data" rows="3" cols="3">
1.064200045753513 -0.053814168552496155 -19.630461688389651 
0.053814168552496155 1.064200045753513 -120.93275372867794 
0 0 1 
</matrix>
		</Matrix>
		<Matrix>
			<matrix id="data" rows="3" cols="3">
1.064037200156094 -0.05538708464047995 -17.388766060353589 
0.05538708464047995 1.064037200156094 -120.6631751306039 
0 0 1 
</matrix>
		</Matrix>
		<Matrix>
			<matrix id="data" rows="3" cols="3">
1.0637368608134092 -0.054808268772583393 -18.307521629000981 
0.054808268772583393 1.0637368608134092 -120.72887726804083 
0 0 1 
</matrix>
		</Matrix>
		<Matrix>
			<matrix id="data" rows="3" cols="3">
1.063472276420242 -0.05382101752095473 -19.349968100692092 
0.05382101752095473 1.063472276420242 -120.20539080064906 
0 0 1 
</matrix>
		</Matrix>
		<Matrix>
			<matrix id="data" rows="3" cols="3">
1.0635680508443091 -0.054814945900740812 -17.941774009834692 
0.054814945900740812 1.0635680508443091 -120.16266243345819 
0 0 1 
</matrix>
		</Matrix>
		<Matrix>
			<matrix id="data" rows="3" cols="3">
1.0634025344915576 -0.054170539569661086 -18.710738715107446 
0.054170539569661086 1.0634025344915576 -120.01874447827835 
0 0 1 
</matrix>
		</Matrix>
		<Matrix>
			<matrix id="data" rows="3" cols="3">
1.0634155169691895 -0.053962499422530959 -19.075451234235043 
0.053962499422530959 1.0634155169691895 -120.21392686653638 
0 0 1 
</matrix>
		</Matrix>
		<Matrix>
			<matrix id="data" rows="3" cols="3">
1.0636096620828512 -0.054937061191375008 -17.704832621616106 
0.054937061191375008 1.0636096620828512 -120.47375604385616 
0 0 1 
</matrix>
		</Matrix>
		<Matrix>
			<matrix id="data" rows="3" cols="3">
1.0634455064637471 -0.053854812655108539 -19.243707383379995 
0.053854812655108539 1.0634455064637471 -120.15374030022949 
0 0 1 
</matrix>
		</Matrix>
		<Matrix>
			<matrix id="data" rows="3" cols="3">
1.0635371444250263 -0.052611558804048372 -20.688411423392782 
0.052611558804048372 1.0635371444250263 -119.9076301166004 
0 0 1 
</matrix>
		</Matrix>
		<Matrix>
			<matrix id="data" rows="3" cols="3">
1.0636958627879738 -0.053837954958192519 -18.524900614421377 
0.053837954958192519 1.0636958627879738 -119.68432512568903 
0 0 1 
</matrix>
		</Matrix>
		<Matrix>
			<matrix id="data" rows="3" cols="3">
1.0641047124311889 -0.053545622305445122 -19.973517486854103 
0.053545622305445122 1.0641047124311889 -120.45996973738623 
0 0 1 
</matrix>
		</Matrix>
		<Matrix>
			<matrix id="data" rows="3" cols="3">
1.0638931194050316 -0.052558617056448327 -19.919508524852464 
0.052558617056448327 1.0638931194050316 -119.34596499065502 
0 0 1 
</matrix>
		</Matrix>
		<Matrix>
			<matrix id="data" rows="3" cols="3">
1.0638755338935104 -0.053272424975358265 -19.284496961354588 
0.053272424975358265 1.0638755338935104 -119.6119830236365 
0 0 1 
</matrix>
		</Matrix>
		<Matrix>
			<matrix id="data" rows="3" cols="3">
1.0635673187905679 -0.052483111631499185 -20.670656531334252 
0.052483111631499185 1.0635673187905679 -119.37718360985932 
0 0 1 
</matrix>
		</Matrix>
		<Matrix>
			<matrix id="data" rows="3" cols="3">
1.064201588783537 -0.052249370877811958 -20.497979729071968 
0.052249370877811958 1.064201588783537 -119.22066187648684 
0 0 1 
</matrix>
		</Matrix>
		<Matrix>
			<matrix id="data" rows="3" cols="3">
1.0641166968170033 -0.052435876539367786 -20.14239036580399 
0.052435876539367786 1.0641166968170033 -119.08631581617078 
0 0 1 
</matrix>
		</Matrix>
		<Matrix>
			<matrix id="data" rows="3" cols="3">
1.064442781902736 -0.050298162864918318 -22.777295759922406 
0.050298162864918318 1.064442781902736 -118.52609178925579 
0 0 1 
</matrix>
		</Matrix>
		<Matrix>
			<matrix id="data" rows="3" cols="3">
1.064351542069115 -0.049942357462045152 -22.564954510134942 
0.049942357462045152 1.064351542069115 -117.8530813220312 
0 0 1 
</matrix>
		</Matrix>
		<Matrix>
			<matrix id="data" rows="3" cols="3">
1.0638951771521405 -0.050731502302054414 -21.488078905862551 
0.050731502302054414 1.0638951771521405 -118.0785318103399 
0 0 1 
</matrix>
		</Matrix>
		<Matrix>
			<matrix id="data" rows="3" cols="3">
1.0640854366383778 -0.049767204653407865 -22.983940651723284 
0.049767204653407865 1.0640854366383778 -117.92903994404351 
0 0 1 
</matrix>
		</Matrix>
		<Matrix>
			<matrix id="data" rows="3" cols="3">
1.0642244945691419 -0.049913108463265396 -22.434164812160443 
0.049913108463265396 1.0642244945691419 -117.90304276347315 
0 0 1 
</matrix>
		</Matrix>
		<Matrix>
			<matrix id="data" rows="3" cols="3">
1.0636978178228411 -0.050527832854373581 -21.520181473588728 
0.050527832854373581 1.0636978178228411 -117.62382672053113 
0 0 1 
</matrix>
		</Matrix>
		<Matrix>
			<matrix id="data" rows="3" cols="3">
1.0642756423479898 -0.049948172445076856 -22.689232175068838 
0.049948172445076856 1.0642756423479898 -118.06334612961581 
0 0 1 
</matrix>
		</Matrix>
		<Matrix>
			<matrix id="data" rows="3" cols="3">
1.0640790952698842 -0.050069826858671319 -22.110478369713118 
0.050069826858671319 1.0640790952698842 -117.6746805929683 
0 0 1 
</matrix>
		</Matrix>
		<Matrix>
			<matrix id="data" rows="3" cols="3">
1.063829889912957 -0.050426709380681077 -22.010621794741379 
0.050426709380681077 1.063829889912957 -118.03425298181811 
0 0 1 
</matrix>
		</Matrix>
		<Matrix>
			<matrix id="data" rows="3" cols="3">
1.0640889858096245 -0.049882641645017677 -22.579433950598343 
0.049882641645017677 1.0640889858096245 -117.68263028304203 
0 0 1 
</matrix>
		</Matrix>
		<Matrix>
			<matrix id="data" rows="3" cols="3">
1.063991406170617 -0.05027468060589145 -21.755999385159178 
0.05027468060589145 1.063991406170617 -117.77153653891352 
0 0 1 
</matrix>
		</Matrix>
		<Matrix>
			<matrix id="data" rows="3" cols="3">
1.0636672431605569 -0.050333826257960707 -20.334206614351555 
0.050333826257960707 1.0636672431605569 -117.54117090710052 
0 0 1 
</matrix>
		</Matrix>
	</list>
</Argos>
