<?xml version="1.0" encoding="utf-8"?>
<Argos version="1.1">
	<list id="homographies">
		<Matrix>
			<matrix id="data" rows="3" cols="3">
1.0000000000000002 -1.1581110910893625e-017 -3.0237650491121704e-013 
1.1581110910893625e-017 1.0000000000000002 -2.7195780349931198e-013 
0 0 1 
</matrix>
		</Matrix>
		<Matrix>
			<matrix id="data" rows="3" cols="3">
0.99999331010296322 -3.8414042934270622e-005 0.019610466401490396 
3.8414042934270622e-005 0.99999331010296322 -0.014122321580051722 
0 0 1 
</matrix>
		</Matrix>
		<Matrix>
			<matrix id="data" rows="3" cols="3">
0.99997262483299088 -6.9629993255125832e-005 0.043140715913394675 
6.9629993255125832e-005 0.99997262483299088 -0.021770598203577782 
0 0 1 
</matrix>
		</Matrix>
		<Matrix>
			<matrix id="data" rows="3" cols="3">
0.9998516455267823 0.00020275658425672444 -0.10196740337469323 
-0.00020275658425672444 0.9998516455267823 0.30511234378406266 
0 0 1 
</matrix>
		</Matrix>
		<Matrix>
			<matrix id="data" rows="3" cols="3">
0.99993059371116022 5.47187257448822e-005 0.01296424386286267 
-5.47187257448822e-005 0.99993059371116022 0.10195545646485518 
0 0 1 
</matrix>
		</Matrix>
		<Matrix>
			<matrix id="data" rows="3" cols="3">
0.99990880105463065 -0.00015621962714445353 0.22024023599438747 
0.00015621962714445353 0.99990880105463065 -0.057649328289963553 
0 0 1 
</matrix>
		</Matrix>
		<Matrix>
			<matrix id="data" rows="3" cols="3">
1.0000090167307734 -1.7019089126805932e-005 -0.0137243250401195 
1.7019089126805932e-005 1.0000090167307734 0.0093699983257162847 
0 0 1 
</matrix>
		</Matrix>
		<Matrix>
			<matrix id="data" rows="3" cols="3">
0.99995186309517603 -1.7191917507359082e-005 0.0036258296015706827 
1.7191917507359082e-005 0.99995186309517603 0.070439169676540694 
0 0 1 
</matrix>
		</Matrix>
		<Matrix>
			<matrix id="data" rows="3" cols="3">
0.99995465727079735 -0.00015430013731631406 0.14564416625125987 
0.00015430013731631406 0.99995465727079735 -0.080539854886673895 
0 0 1 
</matrix>
		</Matrix>
		<Matrix>
			<matrix id="data" rows="3" cols="3">
0.99990886196050555 -6.4615436292689833e-005 0.07597303071379162 
6.4615436292689833e-005 0.99990886196050555 0.038834900455119184 
0 0 1 
</matrix>
		</Matrix>
		<Matrix>
			<matrix id="data" rows="3" cols="3">
0.99993379066476529 -0.00011464097508164425 0.11751109326190437 
0.00011464097508164425 0.99993379066476529 -0.045165598201236203 
0 0 1 
</matrix>
		</Matrix>
		<Matrix>
			<matrix id="data" rows="3" cols="3">
0.99998603824616683 -0.00010694305645828622 0.052386968946428442 
0.00010694305645828622 0.99998603824616683 -0.053653519537393141 
0 0 1 
</matrix>
		</Matrix>
		<Matrix>
			<matrix id="data" rows="3" cols="3">
0.99994800660212813 -0.00011123447931432678 0.10521484226357668 
0.00011123447931432678 0.99994800660212813 -0.047856955327102969 
0 0 1 
</matrix>
		</Matrix>
		<Matrix>
			<matrix id="data" rows="3" cols="3">
0.99993917533484811 -9.6948796641296896e-005 0.11602415701526209 
9.6948796641296896e-005 0.99993917533484811 -0.032069122844862977 
0 0 1 
</matrix>
		</Matrix>
		<Matrix>
			<matrix id="data" rows="3" cols="3">
0.99996051227322802 -5.4291537492287493e-005 0.037632082359745633 
5.4291537492287493e-005 0.99996051227322802 0.021549561108187468 
0 0 1 
</matrix>
		</Matrix>
		<Matrix>
			<matrix id="data" rows="3" cols="3">
0.99994464481541812 -6.8318096678624503e-005 0.090036698386494224 
6.8318096678624503e-005 0.99994464481541812 0.019155006447538054 
0 0 1 
</matrix>
		</Matrix>
		<Matrix>
			<matrix id="data" rows="3" cols="3">
0.99999070521215139 -5.0150852214715666e-005 0.042774719748690238 
5.0150852214715666e-005 0.99999070521215139 0.0087761360812522102 
0 0 1 
</matrix>
		</Matrix>
		<Matrix>
			<matrix id="data" rows="3" cols="3">
1.0000109739127536 -1.4418483007344898e-005 -0.0052456619777429755 
1.4418483007344898e-005 1.0000109739127536 0.046887617972226701 
0 0 1 
</matrix>
		</Matrix>
		<Matrix>
			<matrix id="data" rows="3" cols="3">
1.0000593899142802 1.1099511374876677e-005 -0.062556922687270852 
-1.1099511374876677e-005 1.0000593899142802 0.0090487634181175211 
0 0 1 
</matrix>
		</Matrix>
		<Matrix>
			<matrix id="data" rows="3" cols="3">
0.99992389271783721 0.00050887425989984555 -0.29930142834757295 
-0.00050887425989984555 0.99992389271783721 0.26930456665043495 
0 0 1 
</matrix>
		</Matrix>
		<Matrix>
			<matrix id="data" rows="3" cols="3">
0.99984831727230727 0.00043992302989870856 -0.18223813934544464 
-0.00043992302989870856 0.99984831727230727 0.18639848756243138 
0 0 1 
</matrix>
		</Matrix>
		<Matrix>
			<matrix id="data" rows="3" cols="3">
0.99966031392993293 0.00044361857339784879 0.02485731719520573 
-0.00044361857339784879 0.99966031392993293 0.33594558799046004 
0 0 1 
</matrix>
		</Matrix>
		<Matrix>
			<matrix id="data" rows="3" cols="3">
0.99967232325046573 0.00063603371144727646 -0.17157233400267699 
-0.00063603371144727646 0.99967232325046573 0.59268857581077206 
0 0 1 
</matrix>
		</Matrix>
		<Matrix>
			<matrix id="data" rows="3" cols="3">
0.99961383527581837 0.00047698188561991314 0.070222376169234241 
-0.00047698188561991314 0.99961383527581837 0.37472494755611474 
0 0 1 
</matrix>
		</Matrix>
		<Matrix>
			<matrix id="data" rows="3" cols="3">
0.99981054805329073 0.00036652488063204994 -0.03772075398886221 
-0.00036652488063204994 0.99981054805329073 0.22038215260344368 
0 0 1 
</matrix>
		</Matrix>
		<Matrix>
			<matrix id="data" rows="3" cols="3">
0.99969790964456784 0.0007273362959456511 -0.28694627186999305 
-0.0007273362959456511 0.99969790964456784 0.63855535168691424 
0 0 1 
</matrix>
		</Matrix>
		<Matrix>
			<matrix id="data" rows="3" cols="3">
0.99990296182339744 0.00037825035049386392 -0.10429086121563769 
-0.00037825035049386392 0.99990296182339744 0.079183623150135163 
0 0 1 
</matrix>
		</Matrix>
		<Matrix>
			<matrix id="data" rows="3" cols="3">
0.99990894668536046 0.00051245327799608769 -0.24987464938474574 
-0.00051245327799608769 0.99990894668536046 0.27153965455404988 
0 0 1 
</matrix>
		</Matrix>
		<Matrix>
			<matrix id="data" rows="3" cols="3">
0.99974612182348166 0.00061993022272687805 -0.17581929005935862 
-0.00061993022272687805 0.99974612182348166 0.43362434521043713 
0 0 1 
</matrix>
		</Matrix>
		<Matrix>
			<matrix id="data" rows="3" cols="3">
0.99951036826736728 0.0004588181691945883 0.15578672648921027 
-0.0004588181691945883 0.99951036826736728 0.44277040337568085 
0 0 1 
</matrix>
		</Matrix>
		<Matrix>
			<matrix id="data" rows="3" cols="3">
0.99965717879981753 0.00042188397837868353 0.042757225344816283 
-0.00042188397837868353 0.99965717879981753 0.30252509459994592 
0 0 1 
</matrix>
		</Matrix>
	</list>
</Argos>
